{
  "name": "Hurkacz H. d. Korda S.",
  "attributes": {
    "round": "F",
    "winnerName": "Hurkacz H.",
    "loserName": "Korda S.",
    "score": "6-3 6-3"
  },
  "children": [
    {
      "name": "Hurkacz H. d. Harrison C.",
      "attributes": {
        "round": "SF",
        "winnerName": "Hurkacz H.",
        "loserName": "Harrison C.",
        "score": "7-6 6-4"
      },
      "children": [
        {
          "name": "Hurkacz H. d. Quiroz R.",
          "attributes": {
            "round": "QF",
            "winnerName": "Hurkacz H.",
            "loserName": "Quiroz R.",
            "score": "6-4 6-4"
          },
          "children": [
            {
              "name": "Hurkacz H.",
              "attributes": {
                "round": "4R",
                "winnerName": "Hurkacz H.",
                "loserName": "BYE",
                "score": "BYE"
              },
              "children": []
            },
            {
              "name": "Quiroz R.",
              "attributes": {
                "round": "4R",
                "winnerName": "Quiroz R.",
                "loserName": "BYE",
                "score": "BYE"
              },
              "children": []
            }
          ]
        },
        {
          "name": "Harrison C. d. Mager G.",
          "attributes": {
            "round": "QF",
            "winnerName": "Harrison C.",
            "loserName": "Mager G.",
            "score": "7-6 6-4"
          },
          "children": [
            {
              "name": "Harrison C.",
              "attributes": {
                "round": "4R",
                "winnerName": "Harrison C.",
                "loserName": "BYE",
                "score": "BYE"
              },
              "children": []
            },
            {
              "name": "Mager G.",
              "attributes": {
                "round": "4R",
                "winnerName": "Mager G.",
                "loserName": "BYE",
                "score": "BYE"
              },
              "children": []
            }
          ]
        }
      ]
    },
    {
      "name": "Korda S. d. Norrie C.",
      "attributes": {
        "round": "SF",
        "winnerName": "Korda S.",
        "loserName": "Norrie C.",
        "score": "6-3 7-5"
      },
      "children": [
        {
          "name": "Korda S. d. Isner J.",
          "attributes": {
            "round": "QF",
            "winnerName": "Korda S.",
            "loserName": "Isner J.",
            "score": "6-3 4-6 6-3"
          },
          "children": [
            {
              "name": "Korda S.",
              "attributes": {
                "round": "4R",
                "winnerName": "Korda S.",
                "loserName": "BYE",
                "score": "BYE"
              },
              "children": []
            },
            {
              "name": "Isner J.",
              "attributes": {
                "round": "4R",
                "winnerName": "Isner J.",
                "loserName": "BYE",
                "score": "BYE"
              },
              "children": []
            }
          ]
        },
        {
          "name": "Norrie C. d. Tiafoe F.",
          "attributes": {
            "round": "QF",
            "winnerName": "Norrie C.",
            "loserName": "Tiafoe F.",
            "score": "6-0 3-6 6-4"
          },
          "children": [
            {
              "name": "Norrie C.",
              "attributes": {
                "round": "4R",
                "winnerName": "Norrie C.",
                "loserName": "BYE",
                "score": "BYE"
              },
              "children": []
            },
            {
              "name": "Tiafoe F.",
              "attributes": {
                "round": "4R",
                "winnerName": "Tiafoe F.",
                "loserName": "BYE",
                "score": "BYE"
              },
              "children": []
            }
          ]
        }
      ]
    }
  ]
}