{
  "name": "Tabilo A. d. Daniel T.",
  "attributes": {
    "round": "F",
    "winnerName": "Tabilo A.",
    "loserName": "Daniel T.",
    "score": "6-2 7-5"
  },
  "children": [
    {
      "name": "Tabilo A. d. Fils A.",
      "attributes": {
        "round": "SF",
        "winnerName": "Tabilo A.",
        "loserName": "Fils A.",
        "score": "6-2 7-5"
      },
      "children": [
        {
          "name": "Tabilo A. d. Norrie C.",
          "attributes": {
            "round": "QF",
            "winnerName": "Tabilo A.",
            "loserName": "Norrie C.",
            "score": ""
          },
          "children": [
            {
              "name": "Tabilo A.",
              "attributes": {
                "round": "4R",
                "winnerName": "Tabilo A.",
                "loserName": "BYE",
                "score": "BYE"
              },
              "children": []
            },
            {
              "name": "Norrie C.",
              "attributes": {
                "round": "4R",
                "winnerName": "Norrie C.",
                "loserName": "BYE",
                "score": "BYE"
              },
              "children": []
            }
          ]
        },
        {
          "name": "Fils A. d. Altmaier D.",
          "attributes": {
            "round": "QF",
            "winnerName": "Fils A.",
            "loserName": "Altmaier D.",
            "score": "7-6 1-0 (RET)"
          },
          "children": [
            {
              "name": "Fils A.",
              "attributes": {
                "round": "4R",
                "winnerName": "Fils A.",
                "loserName": "BYE",
                "score": "BYE"
              },
              "children": []
            },
            {
              "name": "Altmaier D.",
              "attributes": {
                "round": "4R",
                "winnerName": "Altmaier D.",
                "loserName": "BYE",
                "score": "BYE"
              },
              "children": []
            }
          ]
        }
      ]
    },
    {
      "name": "Daniel T. d. Shelton B.",
      "attributes": {
        "round": "SF",
        "winnerName": "Daniel T.",
        "loserName": "Shelton B.",
        "score": "7-5 7-6"
      },
      "children": [
        {
          "name": "Daniel T. d. Muller A.",
          "attributes": {
            "round": "QF",
            "winnerName": "Daniel T.",
            "loserName": "Muller A.",
            "score": "6-4 6-7 6-3"
          },
          "children": [
            {
              "name": "Daniel T.",
              "attributes": {
                "round": "4R",
                "winnerName": "Daniel T.",
                "loserName": "BYE",
                "score": "BYE"
              },
              "children": []
            },
            {
              "name": "Muller A.",
              "attributes": {
                "round": "4R",
                "winnerName": "Muller A.",
                "loserName": "BYE",
                "score": "BYE"
              },
              "children": []
            }
          ]
        },
        {
          "name": "Shelton B. d. Carballes Baena R.",
          "attributes": {
            "round": "QF",
            "winnerName": "Shelton B.",
            "loserName": "Carballes Baena R.",
            "score": "6-4 6-3"
          },
          "children": [
            {
              "name": "Shelton B.",
              "attributes": {
                "round": "4R",
                "winnerName": "Shelton B.",
                "loserName": "BYE",
                "score": "BYE"
              },
              "children": []
            },
            {
              "name": "Carballes Baena R.",
              "attributes": {
                "round": "4R",
                "winnerName": "Carballes Baena R.",
                "loserName": "BYE",
                "score": "BYE"
              },
              "children": []
            }
          ]
        }
      ]
    }
  ]
}