{
  "name": "Shelton B. d. Tiafoe F.",
  "attributes": {
    "round": "F",
    "winnerName": "Shelton B.",
    "loserName": "Tiafoe F.",
    "score": "7-5 4-6 6-3"
  },
  "children": [
    {
      "name": "Shelton B. d. Etcheverry T.",
      "attributes": {
        "round": "SF",
        "winnerName": "Shelton B.",
        "loserName": "Etcheverry T.",
        "score": "6-7 6-4 6-4"
      },
      "children": [
        {
          "name": "Shelton B. d. Nakashima B.",
          "attributes": {
            "round": "QF",
            "winnerName": "Shelton B.",
            "loserName": "Nakashima B.",
            "score": "7-5 7-6"
          },
          "children": [
            {
              "name": "Shelton B.",
              "attributes": {
                "round": "4R",
                "winnerName": "Shelton B.",
                "loserName": "BYE",
                "score": "BYE"
              },
              "children": []
            },
            {
              "name": "Nakashima B.",
              "attributes": {
                "round": "4R",
                "winnerName": "Nakashima B.",
                "loserName": "BYE",
                "score": "BYE"
              },
              "children": []
            }
          ]
        },
        {
          "name": "Etcheverry T. d. Mmoh M.",
          "attributes": {
            "round": "QF",
            "winnerName": "Etcheverry T.",
            "loserName": "Mmoh M.",
            "score": "6-3 0-1 (RET)"
          },
          "children": [
            {
              "name": "Etcheverry T.",
              "attributes": {
                "round": "4R",
                "winnerName": "Etcheverry T.",
                "loserName": "BYE",
                "score": "BYE"
              },
              "children": []
            },
            {
              "name": "Mmoh M.",
              "attributes": {
                "round": "4R",
                "winnerName": "Mmoh M.",
                "loserName": "BYE",
                "score": "BYE"
              },
              "children": []
            }
          ]
        }
      ]
    },
    {
      "name": "Tiafoe F. d. Darderi L.",
      "attributes": {
        "round": "SF",
        "winnerName": "Tiafoe F.",
        "loserName": "Darderi L.",
        "score": "6-2 7-6"
      },
      "children": [
        {
          "name": "Tiafoe F. d. Thompson J.",
          "attributes": {
            "round": "QF",
            "winnerName": "Tiafoe F.",
            "loserName": "Thompson J.",
            "score": "7-6 6-4"
          },
          "children": [
            {
              "name": "Tiafoe F.",
              "attributes": {
                "round": "4R",
                "winnerName": "Tiafoe F.",
                "loserName": "BYE",
                "score": "BYE"
              },
              "children": []
            },
            {
              "name": "Thompson J.",
              "attributes": {
                "round": "4R",
                "winnerName": "Thompson J.",
                "loserName": "BYE",
                "score": "BYE"
              },
              "children": []
            }
          ]
        },
        {
          "name": "Darderi L. d. Giron M.",
          "attributes": {
            "round": "QF",
            "winnerName": "Darderi L.",
            "loserName": "Giron M.",
            "score": "6-0 6-4"
          },
          "children": [
            {
              "name": "Darderi L.",
              "attributes": {
                "round": "4R",
                "winnerName": "Darderi L.",
                "loserName": "BYE",
                "score": "BYE"
              },
              "children": []
            },
            {
              "name": "Giron M.",
              "attributes": {
                "round": "4R",
                "winnerName": "Giron M.",
                "loserName": "BYE",
                "score": "BYE"
              },
              "children": []
            }
          ]
        }
      ]
    }
  ]
}