{
  "name": "Monfils G. d. Khachanov K.",
  "attributes": {
    "round": "F",
    "winnerName": "Monfils G.",
    "loserName": "Khachanov K.",
    "score": "6-4 6-4"
  },
  "children": [
    {
      "name": "Monfils G. d. Kokkinakis T.",
      "attributes": {
        "round": "SF",
        "winnerName": "Monfils G.",
        "loserName": "Kokkinakis T.",
        "score": "7-5 6-0"
      },
      "children": [
        {
          "name": "Monfils G. d. Paul T.",
          "attributes": {
            "round": "QF",
            "winnerName": "Monfils G.",
            "loserName": "Paul T.",
            "score": "6-4 6-1"
          },
          "children": [
            {
              "name": "Monfils G.",
              "attributes": {
                "round": "4R",
                "winnerName": "Monfils G.",
                "loserName": "BYE",
                "score": "BYE"
              },
              "children": []
            },
            {
              "name": "Paul T.",
              "attributes": {
                "round": "4R",
                "winnerName": "Paul T.",
                "loserName": "BYE",
                "score": "BYE"
              },
              "children": []
            }
          ]
        },
        {
          "name": "Kokkinakis T. d. Ymer M.",
          "attributes": {
            "round": "QF",
            "winnerName": "Kokkinakis T.",
            "loserName": "Ymer M.",
            "score": "7-6 4-6 6-4"
          },
          "children": [
            {
              "name": "Kokkinakis T.",
              "attributes": {
                "round": "4R",
                "winnerName": "Kokkinakis T.",
                "loserName": "BYE",
                "score": "BYE"
              },
              "children": []
            },
            {
              "name": "Ymer M.",
              "attributes": {
                "round": "4R",
                "winnerName": "Ymer M.",
                "loserName": "BYE",
                "score": "BYE"
              },
              "children": []
            }
          ]
        }
      ]
    },
    {
      "name": "Khachanov K. d. Cilic M.",
      "attributes": {
        "round": "SF",
        "winnerName": "Khachanov K.",
        "loserName": "Cilic M.",
        "score": "7-6 6-3"
      },
      "children": [
        {
          "name": "Khachanov K. d. Gerasimov E.",
          "attributes": {
            "round": "QF",
            "winnerName": "Khachanov K.",
            "loserName": "Gerasimov E.",
            "score": "7-5 6-3"
          },
          "children": [
            {
              "name": "Khachanov K.",
              "attributes": {
                "round": "4R",
                "winnerName": "Khachanov K.",
                "loserName": "BYE",
                "score": "BYE"
              },
              "children": []
            },
            {
              "name": "Gerasimov E.",
              "attributes": {
                "round": "4R",
                "winnerName": "Gerasimov E.",
                "loserName": "BYE",
                "score": "BYE"
              },
              "children": []
            }
          ]
        },
        {
          "name": "Cilic M. d. Djere L.",
          "attributes": {
            "round": "QF",
            "winnerName": "Cilic M.",
            "loserName": "Djere L.",
            "score": "6-3 6-2"
          },
          "children": [
            {
              "name": "Cilic M.",
              "attributes": {
                "round": "4R",
                "winnerName": "Cilic M.",
                "loserName": "BYE",
                "score": "BYE"
              },
              "children": []
            },
            {
              "name": "Djere L.",
              "attributes": {
                "round": "4R",
                "winnerName": "Djere L.",
                "loserName": "BYE",
                "score": "BYE"
              },
              "children": []
            }
          ]
        }
      ]
    }
  ]
}